README.md
setup.py
heluxup/__init__.py
heluxup/main.py
heluxup.egg-info/PKG-INFO
heluxup.egg-info/SOURCES.txt
heluxup.egg-info/dependency_links.txt
heluxup.egg-info/entry_points.txt
heluxup.egg-info/requires.txt
heluxup.egg-info/top_level.txt