Metadata-Version: 2.1
Name: heluxup
Version: 0.1.1
Summary: heluxup makes it easy to upgrade HelmRelease objects in a flux control respository.
Home-page: https://github.com/ekeih/heluxup
Author: Max Rosin
Author-email: heluxup@hackrid.de
License: GPL
Platform: UNKNOWN
Classifier: Programming Language :: Python :: 3
Requires-Python: >=3.7
